natricine/__init__.py
natricine/cqrs/__init__.py
natricine/cqrs/command_bus.py
natricine/cqrs/depends.py
natricine/cqrs/event_bus.py
natricine/cqrs/marshaler.py
natricine/cqrs/py.typed
natricine/cqrs/router.py
natricine/pubsub/__init__.py
natricine/pubsub/memory.py
natricine/pubsub/message.py
natricine/pubsub/publisher.py
natricine/pubsub/py.typed
natricine/pubsub/subscriber.py
natricine/router/__init__.py
natricine/router/handler.py
natricine/router/middleware.py
natricine/router/py.typed
natricine/router/router.py
natricine/router/shutdown.py
natricine/router/types.py
natricine-0.2.0.dist-info/WHEEL
natricine-0.2.0.dist-info/METADATA
natricine-0.2.0.dist-info/RECORD
