Metadata-Version: 2.3
Name: natricine
Version: 0.2.0
Summary: Event-driven architecture toolkit for Python
Requires-Dist: anyio>=4.0
Requires-Dist: pydantic>=2.0 ; extra == 'pydantic'
Requires-Python: >=3.11
Provides-Extra: pydantic
